mregpy/__init__.py
mregpy-0.0.7.dist-info/licenses/LICENSE
mregpy-0.0.7.dist-info/METADATA
mregpy-0.0.7.dist-info/WHEEL
mregpy-0.0.7.dist-info/top_level.txt
mregpy-0.0.7.dist-info/RECORD
